README.rst
setup.py
historybash/__init__.py
historybash.egg-info/PKG-INFO
historybash.egg-info/SOURCES.txt
historybash.egg-info/dependency_links.txt
historybash.egg-info/entry_points.txt
historybash.egg-info/requires.txt
historybash.egg-info/top_level.txt
historybash.egg-info/zip-safe