Metadata-Version: 1.1
Name: historybash
Version: 74
Summary: Bash history command colorized on levenshtein distance of last 10 commands
Home-page: https://github.com/erikdejonge/historybash
Author: Erik de Jonge
Author-email: erik@a8.nl
License: GPL
Platform: UNKNOWN
Classifier: Programming Language :: Python :: 3
Classifier: Intended Audience :: Developers
Classifier: License :: OSI Approved :: GNU Library or Lesser General Public License (LGPL)
Classifier: Operating System :: POSIX
Classifier: Environment :: MacOS X
Classifier: Topic :: System
